sci2pdf
