Metadata-Version: 1.1
Name: sci2pdf
Version: 0.0.3
Summary: Downloads pdfs via a DOI number, article title or a bibtex file, sci-hub
Home-page: https://github.com/bibcure/sci2pdf
Author: Bruno Messias
Author-email: messias.physics@gmail.com
License: GPLv3
Download-URL: https://github.com/bibcure/sci2pdf/archive/0.0.3.tar.gz
Keywords: bibtex,sci-hub,libgen,doi,science,scientific-journals
Platform: UNKNOWN
Classifier: License :: OSI Approved :: GNU General Public License v3 (GPLv3)
Classifier: Intended Audience :: Science/Research
Classifier: Programming Language :: Python
Classifier: Topic :: Text Processing :: Markup :: LaTeX
